{
  "version": "7",
  "dialect": "sqlite",
  "entries": [
    {
      "idx": 0,
      "version": "6",
      "when": 1772969209329,
      "tag": "0000_sloppy_eddie_brock",
      "breakpoints": true
    },
    {
      "idx": 1,
      "version": "6",
      "when": 1773039657034,
      "tag": "0001_low_squirrel_girl",
      "breakpoints": true
    },
    {
      "idx": 2,
      "version": "6",
      "when": 1773040215137,
      "tag": "0002_workable_nitro",
      "breakpoints": true
    },
    {
      "idx": 3,
      "version": "6",
      "when": 1773661707985,
      "tag": "0003_sloppy_doomsday",
      "breakpoints": true
    }
  ]
}